sidetrek_mlflow_plugin/__init__.py
sidetrek_mlflow_plugin/sidetrek_request_header_provider.py
sidetrek_mlflow_plugin-0.0.1.dist-info/METADATA
sidetrek_mlflow_plugin-0.0.1.dist-info/WHEEL
sidetrek_mlflow_plugin-0.0.1.dist-info/entry_points.txt
sidetrek_mlflow_plugin-0.0.1.dist-info/top_level.txt
sidetrek_mlflow_plugin-0.0.1.dist-info/RECORD
